dhdat/ADI.py
dhdat/TauKr.py
dhdat/Ttri.py
dhdat/Xi.py
dhdat/__init__.py
dhdat/bursts.py
dhdat/combinationMaker.py
dhdat/matrix.py
dhdat/networkState.py
dhdat/pairFlips.py
dhdat/triads.py
dhdat-0.6.2.dist-info/METADATA
dhdat-0.6.2.dist-info/WHEEL
dhdat-0.6.2.dist-info/top_level.txt
dhdat-0.6.2.dist-info/zip-safe
dhdat-0.6.2.dist-info/RECORD
