Metadata-Version: 2.1
Name: dhdat
Version: 0.6.2
Summary: DHDAT is a python package with basic tools to produce interaction matrices and calculate several dominance hierarchy related metrics
Home-page: https://github.com/esvanhaeringen/DHDAT
Author: Erik van Haeringen
Author-email: e.s.van.haeringen@student.rug.nl
License: MIT
Platform: UNKNOWN
Classifier: Development Status :: 4 - Beta
Classifier: License :: OSI Approved :: MIT License
Classifier: Programming Language :: Python :: 3
Classifier: Programming Language :: Python :: 3.7
Classifier: Topic :: Scientific/Engineering :: Bio-Informatics
Requires-Dist: pandas
